README.rst
setup.py
everyclient/__init__.py
everyclient/apimixin.py
everyclient/config.py
everyclient/core.py
everyclient/http.py
everyclient.egg-info/PKG-INFO
everyclient.egg-info/SOURCES.txt
everyclient.egg-info/dependency_links.txt
everyclient.egg-info/top_level.txt