Metadata-Version: 1.0
Name: everyclient
Version: 0.1.6
Summary: Everysense client package for Rest API
Home-page: https://github.com/every-sense
Author: Everysense Inc
Author-email: support@every-sense.com
License: MIT
Platform: UNKNOWN
